skym-0.1.0.dist-info/METADATA
skym-0.1.0.dist-info/WHEEL
skym/__init__.py
skym/skym.cpython-313t-x86_64-linux-gnu.so
skym-0.1.0.dist-info/RECORD
