Metadata-Version: 2.4
Name: skym
Version: 0.1.0
Classifier: Programming Language :: Rust
Classifier: Programming Language :: Python :: Implementation :: CPython
Classifier: Programming Language :: Python :: Implementation :: PyPy
Summary: Python package exposing Skim functionality for fuzzy match over an iterable of strings.
Author-email: Ignacio Vergara Kausel <ivergarakausel@gmail.com>
Requires-Python: >=3.8
